<?xml version="1.0" encoding="UTF-8" ?>
<Moudule typeid="4004" Mode="1" WinSwitcherValue="0" WinSwitcherType="0" ChainLayer="0">
    <Mode>
        <mode1 id="1" include="111" WinSwitcherType="0" WinSwitcherValue="0" ChainLayer="0" />
        <mode2 id="2" include="111" WinSwitcherType="0" WinSwitcherValue="0" ChainLayer="0" />
        <mode3 id="3" include="111" WinSwitcherType="0" WinSwitcherValue="0" ChainLayer="0" />
        <mode4 id="4" include="101" WinSwitcherType="0" WinSwitcherValue="0" ChainLayer="0" />
    </Mode>
    <InputList>
        <input1 id="1" default="0" type="PARA_LOGIC" max="1" min="0" InOrOut="PARA_IN" IsPort="0" />
        <input2 id="2" default="0" type="PARA_LOGIC" max="1" min="0" InOrOut="PARA_IN" IsPort="0" />
        <input3 id="3" default="0" type="PARA_LOGIC" max="1" min="0" InOrOut="PARA_OUT" IsPort="0" />
    </InputList>
</Moudule>
